mortgage_filter/__init__.py
mortgage_filter/exceptions.py
mortgage_filter/mortgage_base.py
mortgage_filter/mortgage_filter.py
mortgage_package/__init__.py
mortgage_package/exceptions.py
mortgage_package/mortgage_base.py
mortgage_package/mortgage_filter.py
mortgage_filter_lukavuko-0.2.4.dist-info/LICENSE.md
mortgage_filter_lukavuko-0.2.4.dist-info/METADATA
mortgage_filter_lukavuko-0.2.4.dist-info/WHEEL
mortgage_filter_lukavuko-0.2.4.dist-info/top_level.txt
mortgage_filter_lukavuko-0.2.4.dist-info/RECORD
