Metadata-Version: 2.1
Name: mortgage-filter-lukavuko
Version: 0.2.4
Summary: A package for filtering real estate opportunities based on your financial situation
Home-page: https://github.com/lukavuko/mortgage-filter-package
Author: Luka Vukovic
Author-email: luka.vuko@outlook.com
License: MIT
Platform: UNKNOWN
Classifier: License :: OSI Approved :: MIT License
Classifier: Programming Language :: Python :: 3
Classifier: Programming Language :: Python :: 3.7
Requires-Dist: pandas
Requires-Dist: numpy
